radionets/__init__.py
radionets/_version.py
radionets/version.py
radionets/architecture/__init__.py
radionets/architecture/activation.py
radionets/architecture/archs.py
radionets/architecture/blocks.py
radionets/architecture/layers.py
radionets/architecture/unc_archs.py
radionets/core/__init__.py
radionets/core/callbacks.py
radionets/core/data.py
radionets/core/learner.py
radionets/core/logging.py
radionets/core/loss_functions.py
radionets/core/model.py
radionets/core/utils.py
radionets/evaluation/__init__.py
radionets/evaluation/blob_detection.py
radionets/evaluation/contour.py
radionets/evaluation/dynamic_range.py
radionets/evaluation/jet_angle.py
radionets/evaluation/jets.py
radionets/evaluation/pointsources.py
radionets/evaluation/train_inspection.py
radionets/evaluation/utils.py
radionets/evaluation/scripts/__init__.py
radionets/evaluation/scripts/start_evaluation.py
radionets/plotting/__init__.py
radionets/plotting/_puor.py
radionets/plotting/hist.py
radionets/plotting/inspection.py
radionets/plotting/visualization.py
radionets/simulations/README.md
radionets/simulations/__init__.py
radionets/simulations/gaussians.py
radionets/simulations/point_sources.py
radionets/simulations/sampling.py
radionets/simulations/simulate.py
radionets/simulations/utils.py
radionets/simulations/uv_plots.py
radionets/simulations/uv_simulations.py
radionets/simulations/visualize_simulations.py
radionets/simulations/layouts/__init__.py
radionets/simulations/layouts/layouts.py
radionets/simulations/layouts/vlba.txt
radionets/simulations/scripts/__init__.py
radionets/simulations/scripts/simulate_images.py
radionets/training/__init__.py
radionets/training/utils.py
radionets/training/scripts/__init__.py
radionets/training/scripts/start_training.py
radionets-0.4.1.dist-info/METADATA
radionets-0.4.1.dist-info/WHEEL
radionets-0.4.1.dist-info/entry_points.txt
radionets-0.4.1.dist-info/licenses/LICENSE
radionets-0.4.1.dist-info/RECORD
