Metadata-Version: 2.4
Name: radionets
Version: 0.4.1
Summary: Imaging radio interferometric data with neural networks
Project-URL: Homepage, https://github.com/radionets-project
Project-URL: Repository, https://github.com/radionets-project/radionets
Author: radionets Developers
Maintainer-email: Kevin Schmitz <kevin2.schmitz@tu-dortmund.de>, Anno Knierim <anno.knierim@tu-dortmund.de>
License: MIT
License-File: LICENSE
Classifier: Development Status :: 4 - Beta
Classifier: Intended Audience :: Science/Research
Classifier: License :: OSI Approved :: MIT License
Classifier: Programming Language :: Python :: 3 :: Only
Classifier: Programming Language :: Python :: 3.11
Classifier: Programming Language :: Python :: 3.12
Classifier: Topic :: Scientific/Engineering :: Artificial Intelligence
Classifier: Topic :: Scientific/Engineering :: Astronomy
Classifier: Topic :: Scientific/Engineering :: Information Analysis
Classifier: Topic :: Scientific/Engineering :: Physics
Requires-Python: >=3.11
Requires-Dist: astropy
Requires-Dist: click
Requires-Dist: comet-ml
Requires-Dist: fastai
Requires-Dist: h5py
Requires-Dist: kornia
Requires-Dist: natsort
Requires-Dist: numba
Requires-Dist: numpy
Requires-Dist: pandas
Requires-Dist: pytorch-msssim
Requires-Dist: rich
Requires-Dist: scikit-image
Requires-Dist: toml
Requires-Dist: torch
Requires-Dist: tqdm
Provides-Extra: plot
Requires-Dist: matplotlib; extra == 'plot'
